aiobotocore-stubs/__init__.pyi
aiobotocore-stubs/client.pyi
aiobotocore-stubs/response.pyi
aiobotocore_stubs-0.0.2.data/data/LICENSE
aiobotocore_types/__init__.py
aiobotocore_types/s3_meta_types.py
aiobotocore_types/s3_responses.py
aiobotocore_stubs-0.0.2.dist-info/LICENSE
aiobotocore_stubs-0.0.2.dist-info/METADATA
aiobotocore_stubs-0.0.2.dist-info/WHEEL
aiobotocore_stubs-0.0.2.dist-info/top_level.txt
aiobotocore_stubs-0.0.2.dist-info/RECORD
