Metadata-Version: 2.1
Name: aiobotocore-stubs
Version: 0.0.2
Summary: aiobotocore stubs for typing
Home-page: https://github.com/galavasteg/aiobotocore-stubs
Author-email: galavasteg@gmail.com
License: BSD
Platform: UNKNOWN
Classifier: Development Status :: 3 - Alpha
Classifier: Environment :: Web Environment
Classifier: Intended Audience :: Developers
Classifier: License :: OSI Approved :: BSD License
Classifier: Operating System :: OS Independent
Classifier: Topic :: Internet :: WWW/HTTP
Classifier: Programming Language :: Python :: 3.8
Classifier: Typing :: Typed
Requires-Python: >=3.8
Requires-Dist: aiobotocore (<2,>=1.1.2)
